lcblp/__init__.py
lcblp/config.py
lcblp/datasets.py
lcblp/getSegMask_function.py
lcblp/getSegMask_function_example.py
lcblp/losses.py
lcblp/miniPatch_preprocessing.py
lcblp/models.py
lcblp/preprocessing_miniPatch_example.py
lcblp/transforms.py
lcblp/utils.py
lcblp/wrapper.py
lcblp/networks/__init__.py
lcblp/networks/deeplabv3.py
lcblp/networks/enet.py
lcblp/networks/fcn.py
lcblp/networks/segformer.py
lcblp/networks/stdcseg.py
lcblp-0.0.12.dist-info/METADATA
lcblp-0.0.12.dist-info/WHEEL
lcblp-0.0.12.dist-info/top_level.txt
lcblp-0.0.12.dist-info/RECORD
